[{"minLOD":"lod8","scriptFilePath":null,"message":"export","version":1,"resolution":"4K","resolutionValue":"4096","category":"Foliage","type":"3d","id":"ujcxeblva","name":"Half Avocado","path":"D:\\1_BrickGE\\project_space\\res\\models\\edible_fruit_ujcxeblva","exportAs":"default","textureFormat":"image/jpeg","meshFormat":"application/x-obj","previewImage":"D:\\1_BrickGE\\project_space\\res\\models\\edible_fruit_ujcxeblva\\preview.png","averageColor":"#402B14","tags":["green","brown","yellow","edibles","kitchen","grocery","indoors","table top","avocado","seed","fruit","chopped","fresh","fleshy","half"],"activeLOD":"lod0","categories":["3d","edible","fruit"],"isExternal":false,"exportPath":"D:\\1_BrickGE\\project_space\\res\\models","namingConvention":"$id_$resolution$variation_$mapName$lod","folderNamingConvention":"ujcxeblva__","mapNameOverride":{"Albedo":"Albedo","AO":"AO","Brush":"Brush","Bump":"Bump","Cavity":"Cavity","Curvature":"Curvature","Diffuse":"Diffuse","Displacement":"Displacement","Fuzz":"Fuzz","Gloss":"Gloss","Metalness":"Metalness","Normal":"Normal","Opacity":"Opacity","Roughness":"Roughness","Specular":"Specular","Thickness":"Thickness","Translucency":"Translucency"},"meta":[{"key":"assembly","name":"Assembly","value":"false"},{"key":"small3dasset","name":"Small3dAsset","value":"true"},{"key":"color","name":"Color","value":"Green"},{"key":"points","name":"Points","value":4},{"key":"texelDensity","name":"Texel Density","value":"17652 px/m"},{"key":"splitSubmeshes","name":"Split Submeshes","value":true},{"value":"0.08m","name":"Length","key":"length"},{"value":"0.06m","name":"Width","key":"width"},{"value":"0.05m","name":"Height","key":"height"}],"workflow":"specular","components":[{"format":"jpg","type":"albedo","resolution":"4K","name":"ujcxeblva_4K_Albedo 1.jpg","nameOverride":"ujcxeblva_4K_Albedo.jpg","path":"D:\\1_BrickGE\\project_space\\res\\models\\edible_fruit_ujcxeblva\\ujcxeblva_4K_Albedo 1.jpg"},{"format":"jpg","type":"ao","resolution":"4K","name":"ujcxeblva_4K_AO 1.jpg","nameOverride":"ujcxeblva_4K_AO.jpg","path":"D:\\1_BrickGE\\project_space\\res\\models\\edible_fruit_ujcxeblva\\ujcxeblva_4K_AO 1.jpg"},{"format":"jpg","type":"displacement","resolution":"4K","name":"ujcxeblva_4K_Displacement 1.jpg","nameOverride":"ujcxeblva_4K_Displacement.jpg","path":"D:\\1_BrickGE\\project_space\\res\\models\\edible_fruit_ujcxeblva\\ujcxeblva_4K_Displacement 1.jpg"},{"format":"jpg","type":"gloss","resolution":"4K","name":"ujcxeblva_4K_Gloss 1.jpg","nameOverride":"ujcxeblva_4K_Gloss.jpg","path":"D:\\1_BrickGE\\project_space\\res\\models\\edible_fruit_ujcxeblva\\ujcxeblva_4K_Gloss 1.jpg"},{"format":"jpg","type":"normal","resolution":"4K","name":"ujcxeblva_4K_NormalLOD0 1.jpg","nameOverride":"ujcxeblva_4K_NormalNormalLOD0 1.jpg","path":"D:\\1_BrickGE\\project_space\\res\\models\\edible_fruit_ujcxeblva\\ujcxeblva_4K_NormalLOD0 1.jpg"},{"format":"jpg","type":"roughness","resolution":"4K","name":"ujcxeblva_4K_Roughness 1.jpg","nameOverride":"ujcxeblva_4K_Roughness.jpg","path":"D:\\1_BrickGE\\project_space\\res\\models\\edible_fruit_ujcxeblva\\ujcxeblva_4K_Roughness 1.jpg"},{"format":"jpg","type":"specular","resolution":"4K","name":"ujcxeblva_4K_Specular 1.jpg","nameOverride":"ujcxeblva_4K_Specular.jpg","path":"D:\\1_BrickGE\\project_space\\res\\models\\edible_fruit_ujcxeblva\\ujcxeblva_4K_Specular 1.jpg"}],"components-billboard":[{"path":"D:\\MegascansLibrary\\Downloaded\\3d\\edible_fruit_ujcxeblva\\ujcxeblva_4K_Albedo.jpg","type":"albedo","resolution":"4K"},{"path":"D:\\MegascansLibrary\\Downloaded\\3d\\edible_fruit_ujcxeblva\\ujcxeblva_4K_AO.jpg","type":"ao","resolution":"4K"},{"path":"D:\\MegascansLibrary\\Downloaded\\3d\\edible_fruit_ujcxeblva\\ujcxeblva_4K_Displacement.jpg","type":"displacement","resolution":"4K"},{"path":"D:\\MegascansLibrary\\Downloaded\\3d\\edible_fruit_ujcxeblva\\ujcxeblva_4K_Gloss.jpg","type":"gloss","resolution":"4K"},{"path":"D:\\MegascansLibrary\\Downloaded\\3d\\edible_fruit_ujcxeblva\\ujcxeblva_4K_Normal_LOD0.jpg","type":"normal","resolution":"4K"},{"path":"D:\\MegascansLibrary\\Downloaded\\3d\\edible_fruit_ujcxeblva\\ujcxeblva_4K_Roughness.jpg","type":"roughness","resolution":"4K"},{"path":"D:\\MegascansLibrary\\Downloaded\\3d\\edible_fruit_ujcxeblva\\ujcxeblva_4K_Specular.jpg","type":"specular","resolution":"4K"}],"meshList":[{"format":"obj","type":"model","resolution":"4K","name":"ujcxeblva__LOD0 1.obj","nameOverride":"ujcxeblva__LOD0 1.obj","path":"D:\\1_BrickGE\\project_space\\res\\models\\edible_fruit_ujcxeblva\\ujcxeblva__LOD0 1.obj"}],"packedTextures":[],"lodList":[{"lod":"lod0","path":"D:\\MegascansLibrary\\Downloaded\\3d\\edible_fruit_ujcxeblva\\ujcxeblva_LOD0.obj","name":"ujcxeblva_LOD0.obj","nameOverride":"ujcxeblva__LOD0.obj","lodObjectName":"ujcxeblva__LOD0","format":".obj","type":"model"}],"meshVersion":1,"isCustom":false}]